{
  "$schema": "../gen/schemas/desktop-schema.json",
  "identifier": "default",
  "description": "Capability for the main window",
  "windows": [
    "main"
  ],
  "permissions": [
    "core:default",
    "opener:default",
    "store:default",
    "sql:default",
    "log:default",
    "sql:allow-execute",
    "core:window:default",
    "core:window:allow-start-dragging",
    "core:window:allow-maximize",
    "core:window:allow-minimize",
    "core:window:allow-close",
    "core:window:allow-toggle-maximize",
    "dialog:default",
    "fs:default",
    "fs:default"
  ]
}